great_expectations_zipcode_expectations/__init__.py
great_expectations_zipcode_expectations/expectations/__init__.py
great_expectations_zipcode_expectations/expectations/expect_column_values_to_be_us_zipcode_within_mile_radius_of_given_zipcode.py
great_expectations_zipcode_expectations/expectations/expect_column_values_to_be_valid_alabama_zip.py
great_expectations_zipcode_expectations/expectations/expect_column_values_to_be_valid_alaska_zip.py
great_expectations_zipcode_expectations/expectations/expect_column_values_to_be_valid_arizona_zip.py
great_expectations_zipcode_expectations/expectations/expect_column_values_to_be_valid_arkansas_zip.py
great_expectations_zipcode_expectations/expectations/expect_column_values_to_be_valid_california_zip.py
great_expectations_zipcode_expectations/expectations/expect_column_values_to_be_valid_colorado_zip.py
great_expectations_zipcode_expectations/expectations/expect_column_values_to_be_valid_connecticut_zip.py
great_expectations_zipcode_expectations/expectations/expect_column_values_to_be_valid_delaware_zip.py
great_expectations_zipcode_expectations/expectations/expect_column_values_to_be_valid_florida_zip.py
great_expectations_zipcode_expectations/expectations/expect_column_values_to_be_valid_general_zipcode.py
great_expectations_zipcode_expectations/expectations/expect_column_values_to_be_valid_georgia_zip.py
great_expectations_zipcode_expectations/expectations/expect_column_values_to_be_valid_hawaii_zip.py
great_expectations_zipcode_expectations/expectations/expect_column_values_to_be_valid_idaho_zip.py
great_expectations_zipcode_expectations/expectations/expect_column_values_to_be_valid_illinois_zip.py
great_expectations_zipcode_expectations/expectations/expect_column_values_to_be_valid_india_zip.py
great_expectations_zipcode_expectations/expectations/expect_column_values_to_be_valid_indiana_zip.py
great_expectations_zipcode_expectations/expectations/expect_column_values_to_be_valid_iowa_zip.py
great_expectations_zipcode_expectations-0.1.0.dist-info/LICENSE
great_expectations_zipcode_expectations-0.1.0.dist-info/METADATA
great_expectations_zipcode_expectations-0.1.0.dist-info/WHEEL
great_expectations_zipcode_expectations-0.1.0.dist-info/top_level.txt
great_expectations_zipcode_expectations-0.1.0.dist-info/RECORD
